[
    {
        "name": "Rajah",
        "base": "assets/img/robots/bases/robot3.png",
        "url": "assets/img/robots/robot11737.png",
        "color": "#fbab60",
        "uri": "rajah"
    },
    {
        "name": "Rajah",
        "base": "assets/img/robots/bases/robot8.png",
        "url": "assets/img/robots/robot11738.png",
        "color": "#fbab60",
        "uri": "rajah"
    },
    {
        "name": "Rajah",
        "base": "assets/img/robots/bases/robot14.png",
        "url": "assets/img/robots/robot11739.png",
        "color": "#fbab60",
        "uri": "rajah"
    },
    {
        "name": "Rajah",
        "base": "assets/img/robots/bases/robot11.png",
        "url": "assets/img/robots/robot11740.png",
        "color": "#fbab60",
        "uri": "rajah"
    },
    {
        "name": "Rajah",
        "base": "assets/img/robots/bases/robot18.png",
        "url": "assets/img/robots/robot11741.png",
        "color": "#fbab60",
        "uri": "rajah"
    },
    {
        "name": "Rajah",
        "base": "assets/img/robots/bases/robot9.png",
        "url": "assets/img/robots/robot11742.png",
        "color": "#fbab60",
        "uri": "rajah"
    },
    {
        "name": "Rajah",
        "base": "assets/img/robots/bases/robot10.png",
        "url": "assets/img/robots/robot11743.png",
        "color": "#fbab60",
        "uri": "rajah"
    },
    {
        "name": "Rajah",
        "base": "assets/img/robots/bases/robot7.png",
        "url": "assets/img/robots/robot11744.png",
        "color": "#fbab60",
        "uri": "rajah"
    },
    {
        "name": "Rajah",
        "base": "assets/img/robots/bases/robot15.png",
        "url": "assets/img/robots/robot11745.png",
        "color": "#fbab60",
        "uri": "rajah"
    },
    {
        "name": "Rajah",
        "base": "assets/img/robots/bases/robot6.png",
        "url": "assets/img/robots/robot11746.png",
        "color": "#fbab60",
        "uri": "rajah"
    },
    {
        "name": "Rajah",
        "base": "assets/img/robots/bases/robot1.png",
        "url": "assets/img/robots/robot11747.png",
        "color": "#fbab60",
        "uri": "rajah"
    },
    {
        "name": "Rajah",
        "base": "assets/img/robots/bases/robot12.png",
        "url": "assets/img/robots/robot11748.png",
        "color": "#fbab60",
        "uri": "rajah"
    },
    {
        "name": "Rajah",
        "base": "assets/img/robots/bases/robot2.png",
        "url": "assets/img/robots/robot11749.png",
        "color": "#fbab60",
        "uri": "rajah"
    },
    {
        "name": "Rajah",
        "base": "assets/img/robots/bases/robot16.png",
        "url": "assets/img/robots/robot11750.png",
        "color": "#fbab60",
        "uri": "rajah"
    },
    {
        "name": "Rajah",
        "base": "assets/img/robots/bases/robot4.png",
        "url": "assets/img/robots/robot11751.png",
        "color": "#fbab60",
        "uri": "rajah"
    },
    {
        "name": "Rajah",
        "base": "assets/img/robots/bases/robot5.png",
        "url": "assets/img/robots/robot11752.png",
        "color": "#fbab60",
        "uri": "rajah"
    },
    {
        "name": "Rajah",
        "base": "assets/img/robots/bases/robot19.png",
        "url": "assets/img/robots/robot11753.png",
        "color": "#fbab60",
        "uri": "rajah"
    },
    {
        "name": "Rajah",
        "base": "assets/img/robots/bases/robot17.png",
        "url": "assets/img/robots/robot11754.png",
        "color": "#fbab60",
        "uri": "rajah"
    }
]