[
    {
        "name": "Dark Orchid",
        "base": "assets/img/robots/bases/robot3.png",
        "url": "assets/img/robots/robot3997.png",
        "color": "#9932cc",
        "uri": "dark_orchid"
    },
    {
        "name": "Dark Orchid",
        "base": "assets/img/robots/bases/robot8.png",
        "url": "assets/img/robots/robot3998.png",
        "color": "#9932cc",
        "uri": "dark_orchid"
    },
    {
        "name": "Dark Orchid",
        "base": "assets/img/robots/bases/robot14.png",
        "url": "assets/img/robots/robot3999.png",
        "color": "#9932cc",
        "uri": "dark_orchid"
    },
    {
        "name": "Dark Orchid",
        "base": "assets/img/robots/bases/robot11.png",
        "url": "assets/img/robots/robot4000.png",
        "color": "#9932cc",
        "uri": "dark_orchid"
    },
    {
        "name": "Dark Orchid",
        "base": "assets/img/robots/bases/robot18.png",
        "url": "assets/img/robots/robot4001.png",
        "color": "#9932cc",
        "uri": "dark_orchid"
    },
    {
        "name": "Dark Orchid",
        "base": "assets/img/robots/bases/robot9.png",
        "url": "assets/img/robots/robot4002.png",
        "color": "#9932cc",
        "uri": "dark_orchid"
    },
    {
        "name": "Dark Orchid",
        "base": "assets/img/robots/bases/robot10.png",
        "url": "assets/img/robots/robot4003.png",
        "color": "#9932cc",
        "uri": "dark_orchid"
    },
    {
        "name": "Dark Orchid",
        "base": "assets/img/robots/bases/robot7.png",
        "url": "assets/img/robots/robot4004.png",
        "color": "#9932cc",
        "uri": "dark_orchid"
    },
    {
        "name": "Dark Orchid",
        "base": "assets/img/robots/bases/robot15.png",
        "url": "assets/img/robots/robot4005.png",
        "color": "#9932cc",
        "uri": "dark_orchid"
    },
    {
        "name": "Dark Orchid",
        "base": "assets/img/robots/bases/robot6.png",
        "url": "assets/img/robots/robot4006.png",
        "color": "#9932cc",
        "uri": "dark_orchid"
    },
    {
        "name": "Dark Orchid",
        "base": "assets/img/robots/bases/robot1.png",
        "url": "assets/img/robots/robot4007.png",
        "color": "#9932cc",
        "uri": "dark_orchid"
    },
    {
        "name": "Dark Orchid",
        "base": "assets/img/robots/bases/robot12.png",
        "url": "assets/img/robots/robot4008.png",
        "color": "#9932cc",
        "uri": "dark_orchid"
    },
    {
        "name": "Dark Orchid",
        "base": "assets/img/robots/bases/robot2.png",
        "url": "assets/img/robots/robot4009.png",
        "color": "#9932cc",
        "uri": "dark_orchid"
    },
    {
        "name": "Dark Orchid",
        "base": "assets/img/robots/bases/robot16.png",
        "url": "assets/img/robots/robot4010.png",
        "color": "#9932cc",
        "uri": "dark_orchid"
    },
    {
        "name": "Dark Orchid",
        "base": "assets/img/robots/bases/robot4.png",
        "url": "assets/img/robots/robot4011.png",
        "color": "#9932cc",
        "uri": "dark_orchid"
    },
    {
        "name": "Dark Orchid",
        "base": "assets/img/robots/bases/robot5.png",
        "url": "assets/img/robots/robot4012.png",
        "color": "#9932cc",
        "uri": "dark_orchid"
    },
    {
        "name": "Dark Orchid",
        "base": "assets/img/robots/bases/robot19.png",
        "url": "assets/img/robots/robot4013.png",
        "color": "#9932cc",
        "uri": "dark_orchid"
    },
    {
        "name": "Dark Orchid",
        "base": "assets/img/robots/bases/robot17.png",
        "url": "assets/img/robots/robot4014.png",
        "color": "#9932cc",
        "uri": "dark_orchid"
    }
]