[
    {
        "name": "Persian Red",
        "base": "assets/img/robots/bases/robot3.png",
        "url": "assets/img/robots/robot11089.png",
        "color": "#c33",
        "uri": "persian_red"
    },
    {
        "name": "Persian Red",
        "base": "assets/img/robots/bases/robot8.png",
        "url": "assets/img/robots/robot11090.png",
        "color": "#c33",
        "uri": "persian_red"
    },
    {
        "name": "Persian Red",
        "base": "assets/img/robots/bases/robot14.png",
        "url": "assets/img/robots/robot11091.png",
        "color": "#c33",
        "uri": "persian_red"
    },
    {
        "name": "Persian Red",
        "base": "assets/img/robots/bases/robot11.png",
        "url": "assets/img/robots/robot11092.png",
        "color": "#c33",
        "uri": "persian_red"
    },
    {
        "name": "Persian Red",
        "base": "assets/img/robots/bases/robot18.png",
        "url": "assets/img/robots/robot11093.png",
        "color": "#c33",
        "uri": "persian_red"
    },
    {
        "name": "Persian Red",
        "base": "assets/img/robots/bases/robot9.png",
        "url": "assets/img/robots/robot11094.png",
        "color": "#c33",
        "uri": "persian_red"
    },
    {
        "name": "Persian Red",
        "base": "assets/img/robots/bases/robot10.png",
        "url": "assets/img/robots/robot11095.png",
        "color": "#c33",
        "uri": "persian_red"
    },
    {
        "name": "Persian Red",
        "base": "assets/img/robots/bases/robot7.png",
        "url": "assets/img/robots/robot11096.png",
        "color": "#c33",
        "uri": "persian_red"
    },
    {
        "name": "Persian Red",
        "base": "assets/img/robots/bases/robot15.png",
        "url": "assets/img/robots/robot11097.png",
        "color": "#c33",
        "uri": "persian_red"
    },
    {
        "name": "Persian Red",
        "base": "assets/img/robots/bases/robot6.png",
        "url": "assets/img/robots/robot11098.png",
        "color": "#c33",
        "uri": "persian_red"
    },
    {
        "name": "Persian Red",
        "base": "assets/img/robots/bases/robot1.png",
        "url": "assets/img/robots/robot11099.png",
        "color": "#c33",
        "uri": "persian_red"
    },
    {
        "name": "Persian Red",
        "base": "assets/img/robots/bases/robot12.png",
        "url": "assets/img/robots/robot11100.png",
        "color": "#c33",
        "uri": "persian_red"
    },
    {
        "name": "Persian Red",
        "base": "assets/img/robots/bases/robot2.png",
        "url": "assets/img/robots/robot11101.png",
        "color": "#c33",
        "uri": "persian_red"
    },
    {
        "name": "Persian Red",
        "base": "assets/img/robots/bases/robot16.png",
        "url": "assets/img/robots/robot11102.png",
        "color": "#c33",
        "uri": "persian_red"
    },
    {
        "name": "Persian Red",
        "base": "assets/img/robots/bases/robot4.png",
        "url": "assets/img/robots/robot11103.png",
        "color": "#c33",
        "uri": "persian_red"
    },
    {
        "name": "Persian Red",
        "base": "assets/img/robots/bases/robot5.png",
        "url": "assets/img/robots/robot11104.png",
        "color": "#c33",
        "uri": "persian_red"
    },
    {
        "name": "Persian Red",
        "base": "assets/img/robots/bases/robot19.png",
        "url": "assets/img/robots/robot11105.png",
        "color": "#c33",
        "uri": "persian_red"
    },
    {
        "name": "Persian Red",
        "base": "assets/img/robots/bases/robot17.png",
        "url": "assets/img/robots/robot11106.png",
        "color": "#c33",
        "uri": "persian_red"
    }
]