[
    {
        "name": "Olive Drab #7",
        "base": "assets/img/robots/bases/robot3.png",
        "url": "assets/img/robots/robot9775.png",
        "color": "#3c341f",
        "uri": "olive_drab_7"
    },
    {
        "name": "Olive Drab #7",
        "base": "assets/img/robots/bases/robot8.png",
        "url": "assets/img/robots/robot9776.png",
        "color": "#3c341f",
        "uri": "olive_drab_7"
    },
    {
        "name": "Olive Drab #7",
        "base": "assets/img/robots/bases/robot14.png",
        "url": "assets/img/robots/robot9777.png",
        "color": "#3c341f",
        "uri": "olive_drab_7"
    },
    {
        "name": "Olive Drab #7",
        "base": "assets/img/robots/bases/robot11.png",
        "url": "assets/img/robots/robot9778.png",
        "color": "#3c341f",
        "uri": "olive_drab_7"
    },
    {
        "name": "Olive Drab #7",
        "base": "assets/img/robots/bases/robot18.png",
        "url": "assets/img/robots/robot9779.png",
        "color": "#3c341f",
        "uri": "olive_drab_7"
    },
    {
        "name": "Olive Drab #7",
        "base": "assets/img/robots/bases/robot9.png",
        "url": "assets/img/robots/robot9780.png",
        "color": "#3c341f",
        "uri": "olive_drab_7"
    },
    {
        "name": "Olive Drab #7",
        "base": "assets/img/robots/bases/robot10.png",
        "url": "assets/img/robots/robot9781.png",
        "color": "#3c341f",
        "uri": "olive_drab_7"
    },
    {
        "name": "Olive Drab #7",
        "base": "assets/img/robots/bases/robot7.png",
        "url": "assets/img/robots/robot9782.png",
        "color": "#3c341f",
        "uri": "olive_drab_7"
    },
    {
        "name": "Olive Drab #7",
        "base": "assets/img/robots/bases/robot15.png",
        "url": "assets/img/robots/robot9783.png",
        "color": "#3c341f",
        "uri": "olive_drab_7"
    },
    {
        "name": "Olive Drab #7",
        "base": "assets/img/robots/bases/robot6.png",
        "url": "assets/img/robots/robot9784.png",
        "color": "#3c341f",
        "uri": "olive_drab_7"
    },
    {
        "name": "Olive Drab #7",
        "base": "assets/img/robots/bases/robot1.png",
        "url": "assets/img/robots/robot9785.png",
        "color": "#3c341f",
        "uri": "olive_drab_7"
    },
    {
        "name": "Olive Drab #7",
        "base": "assets/img/robots/bases/robot12.png",
        "url": "assets/img/robots/robot9786.png",
        "color": "#3c341f",
        "uri": "olive_drab_7"
    },
    {
        "name": "Olive Drab #7",
        "base": "assets/img/robots/bases/robot2.png",
        "url": "assets/img/robots/robot9787.png",
        "color": "#3c341f",
        "uri": "olive_drab_7"
    },
    {
        "name": "Olive Drab #7",
        "base": "assets/img/robots/bases/robot16.png",
        "url": "assets/img/robots/robot9788.png",
        "color": "#3c341f",
        "uri": "olive_drab_7"
    },
    {
        "name": "Olive Drab #7",
        "base": "assets/img/robots/bases/robot4.png",
        "url": "assets/img/robots/robot9789.png",
        "color": "#3c341f",
        "uri": "olive_drab_7"
    },
    {
        "name": "Olive Drab #7",
        "base": "assets/img/robots/bases/robot5.png",
        "url": "assets/img/robots/robot9790.png",
        "color": "#3c341f",
        "uri": "olive_drab_7"
    },
    {
        "name": "Olive Drab #7",
        "base": "assets/img/robots/bases/robot19.png",
        "url": "assets/img/robots/robot9791.png",
        "color": "#3c341f",
        "uri": "olive_drab_7"
    },
    {
        "name": "Olive Drab #7",
        "base": "assets/img/robots/bases/robot17.png",
        "url": "assets/img/robots/robot9792.png",
        "color": "#3c341f",
        "uri": "olive_drab_7"
    }
]