[
    {
        "name": "Columbia Blue",
        "base": "assets/img/robots/bases/robot3.png",
        "url": "assets/img/robots/robot3133.png",
        "color": "#9bddff",
        "uri": "columbia_blue"
    },
    {
        "name": "Columbia Blue",
        "base": "assets/img/robots/bases/robot8.png",
        "url": "assets/img/robots/robot3134.png",
        "color": "#9bddff",
        "uri": "columbia_blue"
    },
    {
        "name": "Columbia Blue",
        "base": "assets/img/robots/bases/robot14.png",
        "url": "assets/img/robots/robot3135.png",
        "color": "#9bddff",
        "uri": "columbia_blue"
    },
    {
        "name": "Columbia Blue",
        "base": "assets/img/robots/bases/robot11.png",
        "url": "assets/img/robots/robot3136.png",
        "color": "#9bddff",
        "uri": "columbia_blue"
    },
    {
        "name": "Columbia Blue",
        "base": "assets/img/robots/bases/robot18.png",
        "url": "assets/img/robots/robot3137.png",
        "color": "#9bddff",
        "uri": "columbia_blue"
    },
    {
        "name": "Columbia Blue",
        "base": "assets/img/robots/bases/robot9.png",
        "url": "assets/img/robots/robot3138.png",
        "color": "#9bddff",
        "uri": "columbia_blue"
    },
    {
        "name": "Columbia Blue",
        "base": "assets/img/robots/bases/robot10.png",
        "url": "assets/img/robots/robot3139.png",
        "color": "#9bddff",
        "uri": "columbia_blue"
    },
    {
        "name": "Columbia Blue",
        "base": "assets/img/robots/bases/robot7.png",
        "url": "assets/img/robots/robot3140.png",
        "color": "#9bddff",
        "uri": "columbia_blue"
    },
    {
        "name": "Columbia Blue",
        "base": "assets/img/robots/bases/robot15.png",
        "url": "assets/img/robots/robot3141.png",
        "color": "#9bddff",
        "uri": "columbia_blue"
    },
    {
        "name": "Columbia Blue",
        "base": "assets/img/robots/bases/robot6.png",
        "url": "assets/img/robots/robot3142.png",
        "color": "#9bddff",
        "uri": "columbia_blue"
    },
    {
        "name": "Columbia Blue",
        "base": "assets/img/robots/bases/robot1.png",
        "url": "assets/img/robots/robot3143.png",
        "color": "#9bddff",
        "uri": "columbia_blue"
    },
    {
        "name": "Columbia Blue",
        "base": "assets/img/robots/bases/robot12.png",
        "url": "assets/img/robots/robot3144.png",
        "color": "#9bddff",
        "uri": "columbia_blue"
    },
    {
        "name": "Columbia Blue",
        "base": "assets/img/robots/bases/robot2.png",
        "url": "assets/img/robots/robot3145.png",
        "color": "#9bddff",
        "uri": "columbia_blue"
    },
    {
        "name": "Columbia Blue",
        "base": "assets/img/robots/bases/robot16.png",
        "url": "assets/img/robots/robot3146.png",
        "color": "#9bddff",
        "uri": "columbia_blue"
    },
    {
        "name": "Columbia Blue",
        "base": "assets/img/robots/bases/robot4.png",
        "url": "assets/img/robots/robot3147.png",
        "color": "#9bddff",
        "uri": "columbia_blue"
    },
    {
        "name": "Columbia Blue",
        "base": "assets/img/robots/bases/robot5.png",
        "url": "assets/img/robots/robot3148.png",
        "color": "#9bddff",
        "uri": "columbia_blue"
    },
    {
        "name": "Columbia Blue",
        "base": "assets/img/robots/bases/robot19.png",
        "url": "assets/img/robots/robot3149.png",
        "color": "#9bddff",
        "uri": "columbia_blue"
    },
    {
        "name": "Columbia Blue",
        "base": "assets/img/robots/bases/robot17.png",
        "url": "assets/img/robots/robot3150.png",
        "color": "#9bddff",
        "uri": "columbia_blue"
    }
]