[
    {
        "name": "Deep Cerise",
        "base": "assets/img/robots/bases/robot3.png",
        "url": "assets/img/robots/robot4519.png",
        "color": "#da3287",
        "uri": "deep_cerise"
    },
    {
        "name": "Deep Cerise",
        "base": "assets/img/robots/bases/robot8.png",
        "url": "assets/img/robots/robot4520.png",
        "color": "#da3287",
        "uri": "deep_cerise"
    },
    {
        "name": "Deep Cerise",
        "base": "assets/img/robots/bases/robot14.png",
        "url": "assets/img/robots/robot4521.png",
        "color": "#da3287",
        "uri": "deep_cerise"
    },
    {
        "name": "Deep Cerise",
        "base": "assets/img/robots/bases/robot11.png",
        "url": "assets/img/robots/robot4522.png",
        "color": "#da3287",
        "uri": "deep_cerise"
    },
    {
        "name": "Deep Cerise",
        "base": "assets/img/robots/bases/robot18.png",
        "url": "assets/img/robots/robot4523.png",
        "color": "#da3287",
        "uri": "deep_cerise"
    },
    {
        "name": "Deep Cerise",
        "base": "assets/img/robots/bases/robot9.png",
        "url": "assets/img/robots/robot4524.png",
        "color": "#da3287",
        "uri": "deep_cerise"
    },
    {
        "name": "Deep Cerise",
        "base": "assets/img/robots/bases/robot10.png",
        "url": "assets/img/robots/robot4525.png",
        "color": "#da3287",
        "uri": "deep_cerise"
    },
    {
        "name": "Deep Cerise",
        "base": "assets/img/robots/bases/robot7.png",
        "url": "assets/img/robots/robot4526.png",
        "color": "#da3287",
        "uri": "deep_cerise"
    },
    {
        "name": "Deep Cerise",
        "base": "assets/img/robots/bases/robot15.png",
        "url": "assets/img/robots/robot4527.png",
        "color": "#da3287",
        "uri": "deep_cerise"
    },
    {
        "name": "Deep Cerise",
        "base": "assets/img/robots/bases/robot6.png",
        "url": "assets/img/robots/robot4528.png",
        "color": "#da3287",
        "uri": "deep_cerise"
    },
    {
        "name": "Deep Cerise",
        "base": "assets/img/robots/bases/robot1.png",
        "url": "assets/img/robots/robot4529.png",
        "color": "#da3287",
        "uri": "deep_cerise"
    },
    {
        "name": "Deep Cerise",
        "base": "assets/img/robots/bases/robot12.png",
        "url": "assets/img/robots/robot4530.png",
        "color": "#da3287",
        "uri": "deep_cerise"
    },
    {
        "name": "Deep Cerise",
        "base": "assets/img/robots/bases/robot2.png",
        "url": "assets/img/robots/robot4531.png",
        "color": "#da3287",
        "uri": "deep_cerise"
    },
    {
        "name": "Deep Cerise",
        "base": "assets/img/robots/bases/robot16.png",
        "url": "assets/img/robots/robot4532.png",
        "color": "#da3287",
        "uri": "deep_cerise"
    },
    {
        "name": "Deep Cerise",
        "base": "assets/img/robots/bases/robot4.png",
        "url": "assets/img/robots/robot4533.png",
        "color": "#da3287",
        "uri": "deep_cerise"
    },
    {
        "name": "Deep Cerise",
        "base": "assets/img/robots/bases/robot5.png",
        "url": "assets/img/robots/robot4534.png",
        "color": "#da3287",
        "uri": "deep_cerise"
    },
    {
        "name": "Deep Cerise",
        "base": "assets/img/robots/bases/robot19.png",
        "url": "assets/img/robots/robot4535.png",
        "color": "#da3287",
        "uri": "deep_cerise"
    },
    {
        "name": "Deep Cerise",
        "base": "assets/img/robots/bases/robot17.png",
        "url": "assets/img/robots/robot4536.png",
        "color": "#da3287",
        "uri": "deep_cerise"
    }
]