[
    {
        "name": "Vegas Gold",
        "base": "assets/img/robots/bases/robot3.png",
        "url": "assets/img/robots/robot14833.png",
        "color": "#c5b358",
        "uri": "vegas_gold"
    },
    {
        "name": "Vegas Gold",
        "base": "assets/img/robots/bases/robot8.png",
        "url": "assets/img/robots/robot14834.png",
        "color": "#c5b358",
        "uri": "vegas_gold"
    },
    {
        "name": "Vegas Gold",
        "base": "assets/img/robots/bases/robot14.png",
        "url": "assets/img/robots/robot14835.png",
        "color": "#c5b358",
        "uri": "vegas_gold"
    },
    {
        "name": "Vegas Gold",
        "base": "assets/img/robots/bases/robot11.png",
        "url": "assets/img/robots/robot14836.png",
        "color": "#c5b358",
        "uri": "vegas_gold"
    },
    {
        "name": "Vegas Gold",
        "base": "assets/img/robots/bases/robot18.png",
        "url": "assets/img/robots/robot14837.png",
        "color": "#c5b358",
        "uri": "vegas_gold"
    },
    {
        "name": "Vegas Gold",
        "base": "assets/img/robots/bases/robot9.png",
        "url": "assets/img/robots/robot14838.png",
        "color": "#c5b358",
        "uri": "vegas_gold"
    },
    {
        "name": "Vegas Gold",
        "base": "assets/img/robots/bases/robot10.png",
        "url": "assets/img/robots/robot14839.png",
        "color": "#c5b358",
        "uri": "vegas_gold"
    },
    {
        "name": "Vegas Gold",
        "base": "assets/img/robots/bases/robot7.png",
        "url": "assets/img/robots/robot14840.png",
        "color": "#c5b358",
        "uri": "vegas_gold"
    },
    {
        "name": "Vegas Gold",
        "base": "assets/img/robots/bases/robot15.png",
        "url": "assets/img/robots/robot14841.png",
        "color": "#c5b358",
        "uri": "vegas_gold"
    },
    {
        "name": "Vegas Gold",
        "base": "assets/img/robots/bases/robot6.png",
        "url": "assets/img/robots/robot14842.png",
        "color": "#c5b358",
        "uri": "vegas_gold"
    },
    {
        "name": "Vegas Gold",
        "base": "assets/img/robots/bases/robot1.png",
        "url": "assets/img/robots/robot14843.png",
        "color": "#c5b358",
        "uri": "vegas_gold"
    },
    {
        "name": "Vegas Gold",
        "base": "assets/img/robots/bases/robot12.png",
        "url": "assets/img/robots/robot14844.png",
        "color": "#c5b358",
        "uri": "vegas_gold"
    },
    {
        "name": "Vegas Gold",
        "base": "assets/img/robots/bases/robot2.png",
        "url": "assets/img/robots/robot14845.png",
        "color": "#c5b358",
        "uri": "vegas_gold"
    },
    {
        "name": "Vegas Gold",
        "base": "assets/img/robots/bases/robot16.png",
        "url": "assets/img/robots/robot14846.png",
        "color": "#c5b358",
        "uri": "vegas_gold"
    },
    {
        "name": "Vegas Gold",
        "base": "assets/img/robots/bases/robot4.png",
        "url": "assets/img/robots/robot14847.png",
        "color": "#c5b358",
        "uri": "vegas_gold"
    },
    {
        "name": "Vegas Gold",
        "base": "assets/img/robots/bases/robot5.png",
        "url": "assets/img/robots/robot14848.png",
        "color": "#c5b358",
        "uri": "vegas_gold"
    },
    {
        "name": "Vegas Gold",
        "base": "assets/img/robots/bases/robot19.png",
        "url": "assets/img/robots/robot14849.png",
        "color": "#c5b358",
        "uri": "vegas_gold"
    },
    {
        "name": "Vegas Gold",
        "base": "assets/img/robots/bases/robot17.png",
        "url": "assets/img/robots/robot14850.png",
        "color": "#c5b358",
        "uri": "vegas_gold"
    }
]